aim_ui/VERSION
aim_ui/__init__.py
aim_ui/build/aim_ui_core.py
aim_ui/build/asset-manifest.json
aim_ui/build/favicon.ico
aim_ui/build/index-template.html
aim_ui/build/index.html
aim_ui/build/index.html.gz
aim_ui/build/manifest.json
aim_ui/build/robots.txt
aim_ui/build/assets/icomoon/icomoonIcons.css
aim_ui/build/assets/icomoon/icomoonIcons.css.gz
aim_ui/build/assets/icomoon/selection.json
aim_ui/build/assets/icomoon/fonts/icomoon.eot
aim_ui/build/assets/icomoon/fonts/icomoon.svg
aim_ui/build/assets/icomoon/fonts/icomoon.ttf
aim_ui/build/assets/icomoon/fonts/icomoon.woff
aim_ui/build/assets/inconsolata/inconsolata.css
aim_ui/build/assets/inconsolata/inconsolata.css.gz
aim_ui/build/assets/inconsolata/fonts/Inconsolata.ttf
aim_ui/build/assets/inter/inter.css
aim_ui/build/assets/inter/inter.css.gz
aim_ui/build/assets/inter/fonts/Inter.ttf
aim_ui/build/static/css/9628.f0a21101.chunk.css
aim_ui/build/static/css/9628.f0a21101.chunk.css.gz
aim_ui/build/static/css/9628.f0a21101.chunk.css.map
aim_ui/build/static/css/App.11696a45.chunk.css
aim_ui/build/static/css/App.11696a45.chunk.css.gz
aim_ui/build/static/css/App.11696a45.chunk.css.map
aim_ui/build/static/css/Apps.b0ad9aab.chunk.css
aim_ui/build/static/css/Apps.b0ad9aab.chunk.css.gz
aim_ui/build/static/css/Apps.b0ad9aab.chunk.css.map
aim_ui/build/static/css/Explorer.68d25825.chunk.css
aim_ui/build/static/css/Explorer.68d25825.chunk.css.gz
aim_ui/build/static/css/Explorer.68d25825.chunk.css.map
aim_ui/build/static/css/Explorers.f0c0b4d4.chunk.css
aim_ui/build/static/css/Explorers.f0c0b4d4.chunk.css.gz
aim_ui/build/static/css/Explorers.f0c0b4d4.chunk.css.map
aim_ui/build/static/css/LineChart.bca6567e.chunk.css
aim_ui/build/static/css/LineChart.bca6567e.chunk.css.gz
aim_ui/build/static/css/LineChart.bca6567e.chunk.css.map
aim_ui/build/static/css/MetricsExplorer.45ad3bc4.chunk.css
aim_ui/build/static/css/MetricsExplorer.45ad3bc4.chunk.css.gz
aim_ui/build/static/css/MetricsExplorer.45ad3bc4.chunk.css.map
aim_ui-4.1.0.dev20231012.dist-info/METADATA
aim_ui-4.1.0.dev20231012.dist-info/WHEEL
aim_ui-4.1.0.dev20231012.dist-info/top_level.txt
aim_ui-4.1.0.dev20231012.dist-info/RECORD
