Metadata-Version: 2.1
Name: aim-ui
Version: 4.1.0.dev20231012
Summary: Aim UI
Home-page: UNKNOWN
License: UNKNOWN
Platform: UNKNOWN
